{
  "Breaker": {
    "ConductingEquipment": {
      "OperationalLimit": [
        "0.0"
      ],
      "BaseVoltage": [
        "132000"
      ]
    },
    "IdentifiedObject": {
      "name": [
        "Breaker1"
      ],
      "mRID": [
        "12345"
      ]
    },
    "Switch": {
      "NormalOpen": [
        "false"
      ],
      "ratedVoltage": [
        "145000.0"
      ]
    },
    "Equipment": {
      "EquipmentContainer": [
        "Substation001"
      ]
    },
    "type": [
      "ACLineSegment"
    ],
    "PowerSystemResource": {
      "Location": [
        "Substation001"
      ]
    }
  }
}