{
  "ShuntCompensator": {
    "Equipment": {
      "nominalVoltage": "11000",
      "equipmentContainer": "Substation1"
    },
    "type": "ShuntCompensator",
    "IdentifiedObject": {
      "name": "ShuntCompensator1",
      "mRID": "shuntCompensator1"
    }
  },
  "VoltageLevel1": {
    "type": "VoltageLevel",
    "VoltageLevel": {
      "nominalVoltage": "11000",
      "Substation": "Substation1"
    },
    "IdentifiedObject": {
      "mRID": "voltageLevel1",
      "name": "VoltageLevel1"
    }
  },
  "Substation1": {
    "IdentifiedObject": {
      "name": "Substation1",
      "mRID": "substation1"
    },
    "type": "Substation"
  }
}